husky_simplex/__init__.py
husky_simplex/husky_simplex.py
husky_simplex-0.0.3.dist-info/METADATA
husky_simplex-0.0.3.dist-info/WHEEL
husky_simplex-0.0.3.dist-info/licenses/LICENSE
husky_simplex-0.0.3.dist-info/RECORD
