Metadata-Version: 2.1
Name: husky_simplex
Version: 0.0.3
Summary: A text pre-processing package
Project-URL: Homepage, https://github.com/Sudhendra/Husky_Simplex
Project-URL: Download URL, https://github.com/Sudhendra/Husky_Simplex/archive/refs/tags/0.0.3.tar.gz
Author-email: "Sudhendra Kambhamettu, Nikhil, Karan, Arya, Harshal" <sudhendrakambhamettu@gmail.com>
License: MIT License
Classifier: License :: OSI Approved :: MIT License
Classifier: Operating System :: OS Independent
Classifier: Programming Language :: Python :: 3
Requires-Python: >=3.7
